{
    "title": "마더텅 100% 실전대비 MP3 중학영어듣기 24회 모의고사 3학년 (2025년) - 16차 개정판",
    "link": "http://www.aladin.co.kr/shop/wproduct.aspx?ItemId=348963915&amp;partner=openAPI&amp;start=api",
    "author": "마더텅 편집부 (지은이)",
    "pubDate": "2024-10-04",
    "description": "전국 16개 시·도 교육청 공동 주관 중학영어듣기 능력 평가 완벽 반영, 서울시 중학영어듣기 문제를 반영하였다. 실제 시험과 동일한 속도, 1.25배 빠른 속도, 1.5배 빠른 속도의 3가지 MP3 파일 제공하고, 회별 QR코드를 통해 스마트 기기로 빠르고 편리한 음원 재생이 가능하다.",
    "isbn": "K772933153",
    "isbn13": "9791168596283",
    "itemId": 348963915,
    "priceSales": 12510,
    "priceStandard": 13900,
    "mallType": "BOOK",
    "stockStatus": "",
    "mileage": 690,
    "cover": "https://image.aladin.co.kr/product/34896/39/coversum/k772933153_1.jpg",
    "categoryId": 76825,
    "categoryName": "국내도서>중학교참고서>중3-문제집>영어(중등3)",
    "publisher": "마더텅",
    "salesPoint": 8850,
    "adult": false,
    "fixedPrice": true,
    "customerReviewRank": 0,
    "seriesInfo": {
        "seriesId": 1214051,
        "seriesLink": "http://www.aladin.co.kr/shop/common/wseriesitem.aspx?SRID=1214051&amp;partner=openAPI",
        "seriesName": "마더텅 100% 실전대비 MP3 중학영어듣기 (2025년) "
    },
    "subInfo": {}
}